LICENSE
mpesa_connect/__init__.py
mpesa_connect/account_balance.py
mpesa_connect/app.py
mpesa_connect/authorization.py
mpesa_connect/b2c.py
mpesa_connect/base.py
mpesa_connect/c2b.py
mpesa_connect/enums.py
mpesa_connect/py.typed
mpesa_connect/stk_push.py
mpesa_connect/transaction_status.py
mpesa_connect/urls.py
mpesa_connect/utils.py
mpesa_connect-0.1.4.dist-info/LICENSE
mpesa_connect-0.1.4.dist-info/METADATA
mpesa_connect-0.1.4.dist-info/WHEEL
mpesa_connect-0.1.4.dist-info/RECORD
