Metadata-Version: 2.1
Name: mpesa-connect
Version: 0.1.4
Summary: A wrapper library for the Daraja Mpesa API
Home-page: https://github.com/enwawerueli/mpesa-connect
License: MIT
Keywords: daraja,mpesa,payment
Author: Emz D
Author-email: seaworndrift@gmail.com
Requires-Python: >=3.8,<4.0
Classifier: License :: OSI Approved :: MIT License
Classifier: Natural Language :: English
Classifier: Operating System :: OS Independent
Classifier: Programming Language :: Python
Classifier: Programming Language :: Python :: 3
Classifier: Programming Language :: Python :: 3.8
Classifier: Programming Language :: Python :: 3.9
Classifier: Programming Language :: Python :: 3.10
Classifier: Programming Language :: Python :: 3.11
Requires-Dist: requests (>=2.28.2,<3.0.0)
Project-URL: Repository, https://github.com/enwawerueli/mpesa-connect
